pyscaffoldext/__init__.py
pyscaffoldext/beeproject/__init__.py
pyscaffoldext/beeproject/extension.py
pyscaffoldext/beeproject/templates/__init__.py
pyscaffoldext/beeproject/templates/__init__.template
pyscaffoldext/beeproject/templates/gitignore_all.template
pyscaffoldext/beeproject/templates/gitignore_data.template
pyscaffoldext/beeproject/templates/logger.template
pyscaffoldext/beeproject/templates/manage.template
pyscaffoldext/beeproject/templates/package_readme.template
pyscaffoldext/beeproject/templates/project_init_py.template
pyscaffoldext/beeproject/templates/readme_md.template
pyscaffoldext/beeproject/templates/run_project_main.template
pyscaffoldext/beeproject/templates/settings.template
pyscaffoldext/beeproject/templates/sphinx_conf.template
pyscaffoldext/beeproject/templates/submanage.template
pyscaffoldext/beeproject/templates/subsettings.template
pyscaffoldext/beeproject/templates/supervisor_ini.template
pyscaffoldext/beeproject/templates/template_ipynb.template
pyscaffoldext/beeproject/templates/train_model_py.template
pyscaffoldext_beeproject-1.0.3.dist-info/AUTHORS.rst
pyscaffoldext_beeproject-1.0.3.dist-info/LICENSE.txt
pyscaffoldext_beeproject-1.0.3.dist-info/METADATA
pyscaffoldext_beeproject-1.0.3.dist-info/WHEEL
pyscaffoldext_beeproject-1.0.3.dist-info/entry_points.txt
pyscaffoldext_beeproject-1.0.3.dist-info/top_level.txt
pyscaffoldext_beeproject-1.0.3.dist-info/RECORD
