Metadata-Version: 2.1
Name: pyscaffoldext-beeproject
Version: 1.0.3
Summary: PyScaffold extension for simple structured projects
Home-page: https://github.com/unlihub/pyscaffoldext-beeproject
Author: brooks
Author-email: brooks.hua@gmail.com
License: mit
Project-URL: Documentation, https://github.com/unlihub/pyscaffoldext-beeproject
Platform: any
Classifier: Development Status :: 4 - Beta
Classifier: Programming Language :: Python
Requires-Dist: pyscaffold (<4.0a0,>=3.2a0)
Requires-Dist: pyscaffoldext-markdown
Provides-Extra: testing
Requires-Dist: flake8 ; extra == 'testing'
Requires-Dist: pytest ; extra == 'testing'
Requires-Dist: pytest-cov ; extra == 'testing'
Requires-Dist: pytest-virtualenv ; extra == 'testing'
Requires-Dist: pytest-xdist ; extra == 'testing'
